dunder.py
dunder-0.1.1.dist-info/DESCRIPTION.rst
dunder-0.1.1.dist-info/METADATA
dunder-0.1.1.dist-info/metadata.json
dunder-0.1.1.dist-info/RECORD
dunder-0.1.1.dist-info/top_level.txt
dunder-0.1.1.dist-info/WHEEL
